{"HISTORY":"<!-- --><br>ColdFusion 9: Added the function.<br>","SYNTAX":"<!-- --><br>SpreadsheetShiftColumns(<i xmlns:fn=\"http:\/\/www.w3.org\/2005\/xpath-functions\" xmlns:fo=\"http:\/\/www.w3.org\/1999\/XSL\/Format\" xmlns:xs=\"http:\/\/www.w3.org\/2001\/XMLSchema\">spreadsheetObj<\/i>, <i xmlns:fn=\"http:\/\/www.w3.org\/2005\/xpath-functions\" xmlns:fo=\"http:\/\/www.w3.org\/1999\/XSL\/Format\" xmlns:xs=\"http:\/\/www.w3.org\/2001\/XMLSchema\">start<\/i>[, <i xmlns:fn=\"http:\/\/www.w3.org\/2005\/xpath-functions\" xmlns:fo=\"http:\/\/www.w3.org\/1999\/XSL\/Format\" xmlns:xs=\"http:\/\/www.w3.org\/2001\/XMLSchema\">cols<\/i>] \r\nSpreadsheetShiftColumns(<i xmlns:fn=\"http:\/\/www.w3.org\/2005\/xpath-functions\" xmlns:fo=\"http:\/\/www.w3.org\/1999\/XSL\/Format\" xmlns:xs=\"http:\/\/www.w3.org\/2001\/XMLSchema\">spreadsheetObj<\/i>, <i xmlns:fn=\"http:\/\/www.w3.org\/2005\/xpath-functions\" xmlns:fo=\"http:\/\/www.w3.org\/1999\/XSL\/Format\" xmlns:xs=\"http:\/\/www.w3.org\/2001\/XMLSchema\">start<\/i>, <i xmlns:fn=\"http:\/\/www.w3.org\/2005\/xpath-functions\" xmlns:fo=\"http:\/\/www.w3.org\/1999\/XSL\/Format\" xmlns:xs=\"http:\/\/www.w3.org\/2001\/XMLSchema\">end [, <i>cols<\/i>]<\/i>)<br>","CATEGORY":"Microsoft Office Integration","PAGENAME":"SpreadsheetShiftColumns","SEEALSO":"<!-- --><br><samp class=\"codeph\"><a href=\"WSc3ff6d0ea77859461172e0811cbec22c24-7478.html\">SpreadsheetAddColumn<\/a><\/samp>, <samp class=\"codeph\"><a href=\"WSe9cbe5cf462523a0-660681012216ab44a6-7fff.html\">SpreadsheetDeleteColumn<\/a><\/samp>, <samp class=\"codeph\"><a href=\"WSc3ff6d0ea77859461172e0811cbec22c24-677c.html\">SpreadsheetDeleteColumns<\/a><\/samp>, <samp class=\"codeph\"><a href=\"WSc3ff6d0ea77859461172e0811cbec22c24-6806.html\">SpreadsheetFormatColumn<\/a><\/samp>, <samp class=\"codeph\"><a href=\"WSc3ff6d0ea77859461172e0811cbec22c24-677a.html\">SpreadsheetFormatColumns<\/a><\/samp>, <samp class=\"codeph\"><a href=\"WSc3ff6d0ea77859461172e0811cbec22c24-676d.html\">SpreadsheetShiftRows<\/a><\/samp><br>","DESCRIPTION":"Shifts one or more columns in Excel spreadsheet object left or right.","LICENCE":"http:\/\/help.adobe.com\/en_US\/ColdFusion\/10.0\/LegalNotices\/index.html","EXAMPLE":"<!-- --><br>The following line shifts columns 6 and 7 two columns to the left.<br>&lt;cfset SpreadsheetShiftColumns(SpreadsheetObj,l0,11,2)&gt;&lt;cfscript&gt; \r\n    \/\/\/We need an absolute path, so get the current directory path. \r\n      theFile=GetDirectoryFromPath(GetCurrentTemplatePath()) &amp; &quot;shiftcolumns.xls&quot;; \r\n    \/\/Create a new Excel spreadsheet object. \r\n    theSheet = SpreadsheetNew(&quot;Expenses&quot;); \r\n    \/\/Set some cell values, indicating their initial location. \r\n    SpreadsheetSetCellValue(theSheet,&quot;Cell D10&quot;,10,4); \r\n    SpreadsheetSetCellValue(theSheet,&quot;Cell E12&quot;,12,5); \r\n    SpreadsheetSetCellValue(theSheet,&quot;Cell F12&quot;,12,6); \r\n    SpreadsheetSetCellValue(theSheet,&quot;Cell G13&quot;,13,7); \r\n    \/\/Shift columns 6 and 7 left 2 columns. \r\n    <strong>SpreadsheetShiftColumns(theSheet,6,7,-2);<\/strong> \r\n&lt;\/cfscript&gt; \r\n \r\n&lt;!--- Write the spreadsheet to a file, replacing any existing file. ---&gt; \r\n&lt;cfspreadsheet action=&quot;write&quot; filename=&quot;#theFile#&quot; name=&quot;theSheet&quot; overwrite=true&gt;<br>","USAGE":"<!-- --><br>","Parameter":[{"DESCRIPTION":"The Excel spreadsheet object in which to make the shift.","Parameter":"spreadsheetObj"},{"DESCRIPTION":"The number of the first, or only, column to shift","Parameter":"start"},{"DESCRIPTION":"The number of the last column to shift. If you omit this parameter, the function shifts a single column.","Parameter":"end"},{"DESCRIPTION":"The positive (right) or negative (left) number of columns by which to shift the columns. If you omit this parameter, the function shifts the column right by one unit.","Parameter":"columns"}]}